{
  "$schema": "https://developer.microsoft.com/json-schemas/fabric/item/report/definition/visualContainer/2.6.0/schema.json",
  "name": "fed46be87c23608255a0",
  "position": {
    "x": 21.827871036504131,
    "y": 16.7906700280801,
    "z": 1006,
    "height": 114.17655619094469,
    "width": 617.89665703334776,
    "tabOrder": 1006
  },
  "visual": {
    "visualType": "cardVisual",
    "query": {
      "queryState": {
        "Data": {
          "projections": [
            {
              "field": {
                "Measure": {
                  "Expression": {
                    "SourceRef": {
                      "Entity": "_Measures"
                    }
                  },
                  "Property": "Gross Revenue"
                }
              },
              "queryRef": "_Measures.Gross Revenue",
              "nativeQueryRef": "Gross Revenue"
            },
            {
              "field": {
                "Measure": {
                  "Expression": {
                    "SourceRef": {
                      "Entity": "_Measures"
                    }
                  },
                  "Property": "Revenue LY"
                }
              },
              "queryRef": "_Measures.Revenue LY",
              "nativeQueryRef": "Revenue LY"
            },
            {
              "field": {
                "Measure": {
                  "Expression": {
                    "SourceRef": {
                      "Entity": "_Measures"
                    }
                  },
                  "Property": "Total Orders"
                }
              },
              "queryRef": "_Measures.Total Orders",
              "nativeQueryRef": "Total Orders"
            },
            {
              "field": {
                "Measure": {
                  "Expression": {
                    "SourceRef": {
                      "Entity": "_Measures"
                    }
                  },
                  "Property": "Total Units Sold"
                }
              },
              "queryRef": "_Measures.Total Units Sold",
              "nativeQueryRef": "Total Units Sold"
            }
          ]
        }
      },
      "sortDefinition": {
        "sort": [
          {
            "field": {
              "Measure": {
                "Expression": {
                  "SourceRef": {
                    "Entity": "_Measures"
                  }
                },
                "Property": "Gross Revenue"
              }
            },
            "direction": "Descending"
          }
        ],
        "isDefaultSort": true
      }
    },
    "drillFilterOtherVisuals": true
  }
}